{
  "file_info": {
    "filename": "MIDV-789_1.avi",
    "organized_at": "2025-09-02T17:22:29.549385",
    "organizer_version": "1.0"
  },
  "metadata": {
    "code": "MIDV-789",
    "title": "MIDV-789ご近所トラブルに巻き込まれて強●参加させられた町内会セクハラ宴会で絶倫オヤジ達と朝まで中出し乱交 中山ふみか 生写真3枚付き",
    "title_en": null,
    "actresses": [
      "中山ふみか",
      "吉村文孝",
      "アベ",
      "ニック"
    ],
    "release_date": "2024-07-17",
    "duration": 2,
    "studio": "Uncensored",
    "series": "Uncensored",
    "genres": [
      "Uncensored",
      "Western",
      "FC2",
      "Anime"
    ],
    "cover_url": "https://c0.jdbstatic.com/covers/yx/yxrgBX.jpg",
    "poster_url": "https://c0.jdbstatic.com/covers/yx/yxrgBX.jpg",
    "screenshots": [
      "https://c0.jdbstatic.com/covers/yx/yxrgBX.jpg",
      "https://c0.jdbstatic.com/samples/yx/yxrgBX_s_0.jpg",
      "https://c0.jdbstatic.com/samples/yx/yxrgBX_s_1.jpg",
      "https://c0.jdbstatic.com/samples/yx/yxrgBX_s_2.jpg",
      "https://c0.jdbstatic.com/samples/yx/yxrgBX_s_3.jpg",
      "https://c0.jdbstatic.com/samples/yx/yxrgBX_s_4.jpg",
      "https://c0.jdbstatic.com/samples/yx/yxrgBX_s_5.jpg",
      "https://c0.jdbstatic.com/samples/yx/yxrgBX_s_6.jpg",
      "https://c0.jdbstatic.com/samples/yx/yxrgBX_s_7.jpg",
      "https://c0.jdbstatic.com/samples/yx/yxrgBX_s_8.jpg",
      "https://c0.jdbstatic.com/samples/yx/yxrgBX_s_9.jpg",
      "https://c0.jdbstatic.com/samples/yx/yxrgBX_s_10.jpg"
    ],
    "description": null,
    "rating": 4.21,
    "source_url": "https://javdb.com/v/yxrgBX",
    "scraped_at": "2025-09-02T17:22:29.548269"
  }
}