{
  "file_info": {
    "filename": "ABP-120_1.mp4",
    "organized_at": "2025-09-02T16:15:29.642055",
    "organizer_version": "1.0"
  },
  "metadata": {
    "code": "ABP-120",
    "title": "Keywords JUL-666 Result",
    "title_en": null,
    "actresses": [],
    "release_date": null,
    "duration": null,
    "studio": "Uncensored",
    "series": "Uncensored",
    "genres": [
      "Uncensored",
      "Western",
      "FC2",
      "Anime"
    ],
    "cover_url": "https://c0.jdbstatic.com/covers/mn/MNXGv.jpg",
    "poster_url": "https://c0.jdbstatic.com/covers/mn/MNXGv.jpg",
    "screenshots": [],
    "description": null,
    "rating": null,
    "source_url": "https://javdb.com/v/Azb3K",
    "scraped_at": "2025-09-02T16:15:29.640584"
  }
}